livekit/plugins/azure/__init__.py
livekit/plugins/azure/log.py
livekit/plugins/azure/py.typed
livekit/plugins/azure/stt.py
livekit/plugins/azure/tts.py
livekit/plugins/azure/version.py
aeon_plugins_azure-0.2.1.dist-info/METADATA
aeon_plugins_azure-0.2.1.dist-info/WHEEL
aeon_plugins_azure-0.2.1.dist-info/top_level.txt
aeon_plugins_azure-0.2.1.dist-info/RECORD
